[{"String":"I can do this all day","Integer":"6","Float":"3.66","Date":"2019-05-24","Boolean":"true"},{"String":"Hala Madrid!","Integer":"1902","Float":"10.13","Date":"2014-05-24","Boolean":"true"},{"String":"Rancaekek","Integer":"1997","Float":"0.1","Date":"1997-06-18","Boolean":"true"},{"String":"Cicalengka","Integer":"10","Float":"10.08","Date":"2007-07-14","Boolean":"false"},{"String":"Wisuda","Integer":"145","Float":"3.66","Date":"1997-07-20","Boolean":"true"},{"String":"First professional job","Integer":"2","Float":"9.1","Date":"2019-06-19","Boolean":"false"},{"String":"Good bye CR7","Integer":"7","Float":"9.08","Date":"2018-07-07","Boolean":"true"}]